{
  "$schema": "../../tooling/src/validators/manifest.schema.json",
  "package": "@dzup-ui/core",
  "version": "0.0.1",
  "description": "Public API manifest for @dzup-ui/core — barrel exports are generated from this file (ADR-01).",
  "exports": {
    "components": {
      "buttons": {
        "path": "./src/components/buttons/index.ts",
        "exports": [
          "DzButton",
          "DzIconButton",
          "DzButtonGroup",
          "DzToggleButton",
          "DzSplitButton",
          "DzSplitButtonAction",
          "DzSplitButtonMenu"
        ]
      },
      "cards": {
        "path": "./src/components/cards/index.ts",
        "exports": [
          "DzCard",
          "DzCardHeader",
          "DzCardBody",
          "DzCardFooter",
          "DzStatCard",
          "DzImageCard"
        ]
      },
      "inputs": {
        "path": "./src/components/inputs/index.ts",
        "exports": [
          "DzInput",
          "DzTextarea",
          "DzNumberInput",
          "DzPasswordInput",
          "DzSearchInput",
          "DzInputGroup",
          "DzOtpInput"
        ]
      },
      "forms": {
        "path": "./src/components/forms/index.ts",
        "exports": [
          "DzFormField",
          "DzFormLabel",
          "DzFormDescription",
          "DzFormMessage",
          "DzCheckbox",
          "DzCheckboxGroup",
          "DzRadio",
          "DzRadioGroup",
          "DzSwitch",
          "DzSelect",
          "DzDatePicker",
          "DzDateRangePicker",
          "DzTimePicker",
          "DzMultiSelect",
          "DzCombobox",
          "DzSlider",
          "DzFileUpload",
          "DzColorPicker",
          "DzRangeSlider",
          "DzTransfer"
        ]
      },
      "layout": {
        "path": "./src/components/layout/index.ts",
        "exports": [
          "DzContainer",
          "DzGrid",
          "DzFlex",
          "DzStack",
          "DzDivider",
          "DzSpacer",
          "DzAspectRatio",
          "DzCollapse",
          "DzScrollArea",
          "DzResizable",
          "DzResizablePanel",
          "DzResizableHandle",
          "DzSplitter",
          "DzSplitterPanel",
          "DzSplitterHandle"
        ]
      },
      "navigation": {
        "path": "./src/components/navigation/index.ts",
        "exports": [
          "DzTabs",
          "DzTabList",
          "DzTabTrigger",
          "DzTabContent",
          "DzBreadcrumb",
          "DzBreadcrumbItem",
          "DzBreadcrumbSeparator",
          "DzPagination",
          "DzMenu",
          "DzMenuItem",
          "DzMenuSeparator",
          "DzStepper",
          "DzStepperItem",
          "DzSegmented"
        ]
      },
      "overlays": {
        "path": "./src/components/overlays/index.ts",
        "exports": [
          "DzDialog",
          "DzDialogTrigger",
          "DzDialogOverlay",
          "DzDialogContent",
          "DzDialogTitle",
          "DzDialogDescription",
          "DzDialogClose",
          "DzTooltip",
          "DzTooltipTrigger",
          "DzTooltipContent",
          "DzPopover",
          "DzPopoverTrigger",
          "DzPopoverContent",
          "DzSheet",
          "DzSheetTrigger",
          "DzSheetContent",
          "DzSheetTitle",
          "DzSheetDescription",
          "DzSheetClose",
          "DzDropdownMenu",
          "DzDropdownMenuTrigger",
          "DzDropdownMenuContent",
          "DzDropdownMenuItem",
          "DzDropdownMenuSeparator",
          "DzContextMenu",
          "DzContextMenuTrigger",
          "DzContextMenuContent",
          "DzContextMenuItem",
          "DzContextMenuSeparator",
          "DzCommandPalette"
        ]
      },
      "feedback": {
        "path": "./src/components/feedback/index.ts",
        "exports": [
          "DzAlert",
          "DzBadge",
          "DzProgress",
          "DzSpinner",
          "DzSkeleton",
          "DzToastProvider",
          "DzToast",
          "DzToastViewport",
          "DzEmpty",
          "DzResult",
          "DzNotification"
        ]
      },
      "data": {
        "path": "./src/components/data/index.ts",
        "exports": [
          "DzChip",
          "DzTag",
          "DzList",
          "DzListItem",
          "DzTimeline",
          "DzTimelineItem",
          "DzTable",
          "DzTableHeader",
          "DzTableBody",
          "DzTableRow",
          "DzTableCell",
          "DzAccordion",
          "DzAccordionItem",
          "DzAccordionTrigger",
          "DzAccordionContent",
          "DzDataGrid",
          "DzDataGridHeader",
          "DzDataGridBody",
          "DzDataGridPagination",
          "DzTree",
          "DzTreeItem"
        ]
      },
      "media": {
        "path": "./src/components/media/index.ts",
        "exports": [
          "DzIcon",
          "DzAvatar",
          "DzAvatarGroup",
          "DzImage",
          "DzCarousel",
          "DzCarouselSlide",
          "DzCarouselPrevious",
          "DzCarouselNext",
          "DzCarouselDots",
          "DzLightbox"
        ]
      },
      "typography": {
        "path": "./src/components/typography/index.ts",
        "exports": [
          "DzHeading",
          "DzText",
          "DzCode",
          "DzBlockquote",
          "DzCaption"
        ]
      }
    },
    "composables": {
      "useFormField": {
        "path": "./src/composables/useFormField/index.ts",
        "exports": ["useFormField", "useFormFieldContext", "DZ_FORM_FIELD_KEY"]
      },
      "useDatePicker": {
        "path": "./src/composables/useDatePicker/index.ts",
        "exports": ["useDatePicker"]
      },
      "useToast": {
        "path": "./src/composables/useToast/index.ts",
        "exports": ["useToast"]
      },
      "useCollapse": {
        "path": "./src/composables/useCollapse/index.ts",
        "exports": ["useCollapse"]
      },
      "useDataGrid": {
        "path": "./src/composables/useDataGrid/index.ts",
        "exports": ["useDataGrid"]
      }
    },
    "utilities": {
      "cn": {
        "path": "./src/utilities/cn.ts",
        "exports": ["cn"]
      }
    },
    "injectionKeys": [
      "DZ_BUTTON_GROUP_KEY",
      "DZ_SPLIT_BUTTON_KEY",
      "DZ_CHECKBOX_GROUP_KEY",
      "DZ_TABS_KEY",
      "DZ_BREADCRUMB_KEY",
      "DZ_MENU_KEY",
      "DZ_STEPPER_KEY",
      "DZ_DIALOG_KEY",
      "DZ_TOAST_KEY",
      "DZ_LIST_KEY",
      "DZ_TIMELINE_KEY",
      "DZ_TABLE_KEY",
      "DZ_ACCORDION_KEY",
      "DZ_DATA_GRID_KEY",
      "DZ_TREE_KEY",
      "DZ_AVATAR_GROUP_KEY",
      "DZ_CAROUSEL_KEY",
      "DZ_RESIZABLE_KEY",
      "DZ_SPLITTER_KEY"
    ],
    "variants": [
      "buttonVariants",
      "buttonGroupVariants",
      "toggleButtonVariants",
      "cardVariants",
      "cardHeaderVariants",
      "cardBodyVariants",
      "cardFooterVariants",
      "statCardVariants",
      "imageCardVariants",
      "inputWrapperVariants",
      "inputElementVariants",
      "textareaVariants",
      "inputGroupVariants",
      "otpInputVariants",
      "checkboxVariants",
      "radioVariants",
      "switchVariants",
      "selectVariants",
      "datePickerVariants",
      "dateRangePickerVariants",
      "timePickerVariants",
      "multiSelectVariants",
      "comboboxVariants",
      "sliderVariants",
      "fileUploadVariants",
      "colorPickerVariants",
      "rangeSliderVariants",
      "transferVariants",
      "containerVariants",
      "gridVariants",
      "flexVariants",
      "dividerVariants",
      "scrollAreaVariants",
      "resizableVariants",
      "tabsVariants",
      "breadcrumbVariants",
      "paginationVariants",
      "menuVariants",
      "stepperVariants",
      "segmentedVariants",
      "dialogVariants",
      "tooltipVariants",
      "popoverVariants",
      "sheetVariants",
      "dropdownMenuVariants",
      "contextMenuVariants",
      "commandPaletteVariants",
      "alertVariants",
      "badgeVariants",
      "progressTrackVariants",
      "progressBarVariants",
      "spinnerVariants",
      "skeletonVariants",
      "toastVariants",
      "emptyVariants",
      "resultVariants",
      "notificationVariants",
      "notificationTitleVariants",
      "notificationDescriptionVariants",
      "notificationCloseVariants",
      "chipVariants",
      "tagVariants",
      "listVariants",
      "timelineVariants",
      "tableVariants",
      "accordionVariants",
      "dataGridVariants",
      "treeVariants",
      "iconVariants",
      "avatarVariants",
      "avatarGroupVariants",
      "avatarGroupOverflowVariants",
      "imageVariants",
      "carouselVariants",
      "lightboxVariants",
      "headingVariants",
      "textVariants",
      "codeVariants",
      "blockquoteVariants",
      "captionVariants"
    ],
    "types": [
      "DzButtonProps",
      "DzButtonEmits",
      "DzButtonSlots",
      "DzIconButtonProps",
      "DzIconButtonEmits",
      "DzButtonGroupProps",
      "DzButtonGroupSlots",
      "DzButtonGroupContext",
      "DzToggleButtonProps",
      "DzToggleButtonEmits",
      "DzToggleButtonSlots",
      "DzSplitButtonProps",
      "DzSplitButtonSlots",
      "DzSplitButtonContext",
      "DzSplitButtonActionProps",
      "DzSplitButtonActionEmits",
      "DzSplitButtonActionSlots",
      "DzSplitButtonMenuProps",
      "DzSplitButtonMenuSlots",
      "ButtonVariantProps",
      "ButtonGroupVariantProps",
      "ToggleButtonVariantProps",
      "DzCardProps",
      "DzCardEmits",
      "DzCardSlots",
      "DzCardVariant",
      "DzCardPadding",
      "DzCardHeaderProps",
      "DzCardHeaderSlots",
      "DzCardBodyProps",
      "DzCardBodySlots",
      "DzCardFooterProps",
      "DzCardFooterSlots",
      "CardVariantProps",
      "DzStatCardProps",
      "DzStatCardSlots",
      "StatTrend",
      "StatCardVariant",
      "StatCardVariantProps",
      "DzImageCardProps",
      "DzImageCardSlots",
      "ImageCardVariant",
      "ImageCardVariantProps",
      "DzInputProps",
      "DzInputEmits",
      "DzInputSlots",
      "InputWrapperVariantProps",
      "InputElementVariantProps",
      "DzTextareaProps",
      "DzTextareaEmits",
      "DzTextareaSlots",
      "TextareaVariantProps",
      "DzNumberInputProps",
      "DzNumberInputEmits",
      "DzNumberInputSlots",
      "DzPasswordInputProps",
      "DzPasswordInputEmits",
      "DzPasswordInputSlots",
      "DzSearchInputProps",
      "DzSearchInputEmits",
      "DzSearchInputSlots",
      "DzInputGroupProps",
      "DzInputGroupSlots",
      "InputGroupVariantProps",
      "DzOtpInputProps",
      "DzOtpInputEmits",
      "DzOtpInputSlots",
      "OtpInputVariantProps",
      "DzFormFieldProps",
      "DzFormFieldSlots",
      "DzCheckboxProps",
      "DzCheckboxEmits",
      "DzCheckboxSlots",
      "DzCheckboxGroupProps",
      "DzCheckboxGroupEmits",
      "DzCheckboxGroupSlots",
      "DzCheckboxGroupContext",
      "CheckboxVariantProps",
      "DzRadioProps",
      "DzRadioSlots",
      "DzRadioGroupProps",
      "DzRadioGroupEmits",
      "DzRadioGroupSlots",
      "RadioVariantProps",
      "DzSwitchProps",
      "DzSwitchEmits",
      "DzSwitchSlots",
      "SwitchVariantProps",
      "DzSelectProps",
      "DzSelectEmits",
      "DzSelectSlots",
      "DzSelectItem",
      "SelectVariantProps",
      "DzDatePickerProps",
      "DzDatePickerEmits",
      "DzDatePickerSlots",
      "DatePickerVariantProps",
      "DzDateRangePickerProps",
      "DzDateRangePickerEmits",
      "DzDateRangePickerSlots",
      "DateRangeValue",
      "DateRangePickerVariantProps",
      "DzTimePickerProps",
      "DzTimePickerEmits",
      "DzTimePickerSlots",
      "TimePickerVariantProps",
      "DzMultiSelectProps",
      "DzMultiSelectEmits",
      "DzMultiSelectSlots",
      "MultiSelectVariantProps",
      "DzComboboxProps",
      "DzComboboxEmits",
      "DzComboboxSlots",
      "ComboboxVariantProps",
      "DzSliderProps",
      "DzSliderEmits",
      "DzSliderSlots",
      "SliderVariantProps",
      "DzFileUploadProps",
      "DzFileUploadEmits",
      "DzFileUploadSlots",
      "FileUploadError",
      "FileUploadVariantProps",
      "DzColorPickerProps",
      "DzColorPickerEmits",
      "DzColorPickerSlots",
      "ColorPickerVariantProps",
      "DzRangeSliderProps",
      "DzRangeSliderEmits",
      "DzRangeSliderSlots",
      "RangeSliderVariantProps",
      "DzTransferProps",
      "DzTransferEmits",
      "DzTransferSlots",
      "TransferItem",
      "TransferChangePayload",
      "TransferVariantProps",
      "DzContainerProps",
      "DzContainerSlots",
      "ContainerMaxWidth",
      "ContainerVariantProps",
      "DzGridProps",
      "DzGridSlots",
      "GridCols",
      "LayoutGap",
      "ResponsiveCols",
      "GridVariantProps",
      "DzFlexProps",
      "DzFlexSlots",
      "FlexDirection",
      "FlexAlign",
      "FlexJustify",
      "FlexVariantProps",
      "DzStackProps",
      "DzStackSlots",
      "StackDirection",
      "StackAlign",
      "DzDividerProps",
      "DzDividerSlots",
      "DividerOrientation",
      "DividerVariantProps",
      "DzSpacerProps",
      "DzSpacerSlots",
      "SpacerSize",
      "DzAspectRatioProps",
      "DzAspectRatioSlots",
      "DzCollapseProps",
      "DzCollapseSlots",
      "DzScrollAreaProps",
      "DzScrollAreaSlots",
      "ScrollOrientation",
      "ScrollAreaVariantProps",
      "DzResizableProps",
      "DzResizableEmits",
      "DzResizableSlots",
      "DzResizablePanelProps",
      "DzResizablePanelSlots",
      "DzResizableHandleProps",
      "DzResizableHandleSlots",
      "DzResizableContext",
      "ResizableDirection",
      "ResizableVariantProps",
      "DzSplitterProps",
      "DzSplitterEmits",
      "DzSplitterSlots",
      "DzSplitterPanelProps",
      "DzSplitterPanelSlots",
      "DzSplitterHandleProps",
      "DzSplitterHandleSlots",
      "DzSplitterContext",
      "SplitterDirection",
      "DzTabsProps",
      "DzTabsEmits",
      "DzTabsSlots",
      "DzTabsContext",
      "DzTabListProps",
      "DzTabListSlots",
      "DzTabTriggerProps",
      "DzTabTriggerSlots",
      "DzTabContentProps",
      "DzTabContentSlots",
      "TabsVariantProps",
      "DzBreadcrumbProps",
      "DzBreadcrumbSlots",
      "DzBreadcrumbContext",
      "DzBreadcrumbItemProps",
      "DzBreadcrumbItemSlots",
      "DzBreadcrumbSeparatorProps",
      "DzBreadcrumbSeparatorSlots",
      "BreadcrumbVariantProps",
      "DzPaginationProps",
      "DzPaginationEmits",
      "DzPaginationSlots",
      "PaginationVariantProps",
      "DzMenuProps",
      "DzMenuSlots",
      "DzMenuContext",
      "DzMenuItemProps",
      "DzMenuItemEmits",
      "DzMenuItemSlots",
      "DzMenuSeparatorProps",
      "MenuVariantProps",
      "DzStepperProps",
      "DzStepperEmits",
      "DzStepperSlots",
      "DzStepperContext",
      "DzStepperItemProps",
      "DzStepperItemSlots",
      "StepperOrientation",
      "StepperVariantProps",
      "DzSegmentedProps",
      "DzSegmentedEmits",
      "DzSegmentedSlots",
      "SegmentedItem",
      "SegmentedVariantProps",
      "DzDialogProps",
      "DzDialogContentProps",
      "DzDialogContentEmits",
      "DzDialogSlots",
      "DzDialogTriggerSlots",
      "DzDialogOverlaySlots",
      "DzDialogContentSlots",
      "DzDialogTitleSlots",
      "DzDialogDescriptionSlots",
      "DzDialogCloseSlots",
      "DzDialogContext",
      "DialogContentSize",
      "DialogVariantProps",
      "DzTooltipProps",
      "DzTooltipContentProps",
      "DzTooltipSlots",
      "DzTooltipTriggerSlots",
      "DzTooltipContentSlots",
      "TooltipSide",
      "TooltipAlign",
      "TooltipVariantProps",
      "DzPopoverProps",
      "DzPopoverContentProps",
      "DzPopoverContentEmits",
      "DzPopoverSlots",
      "DzPopoverTriggerSlots",
      "DzPopoverContentSlots",
      "PopoverSide",
      "PopoverAlign",
      "PopoverContentSize",
      "PopoverVariantProps",
      "DzSheetProps",
      "DzSheetSlots",
      "DzSheetContentProps",
      "DzSheetContentEmits",
      "DzSheetContentSlots",
      "DzSheetTriggerSlots",
      "DzSheetCloseSlots",
      "DzSheetTitleSlots",
      "DzSheetDescriptionSlots",
      "SheetSide",
      "SheetVariantProps",
      "DzDropdownMenuProps",
      "DzDropdownMenuSlots",
      "DzDropdownMenuTriggerSlots",
      "DzDropdownMenuContentProps",
      "DzDropdownMenuContentEmits",
      "DzDropdownMenuContentSlots",
      "DzDropdownMenuItemProps",
      "DzDropdownMenuItemEmits",
      "DzDropdownMenuItemSlots",
      "DzDropdownMenuSeparatorSlots",
      "DropdownSide",
      "DropdownAlign",
      "DropdownMenuVariantProps",
      "DzContextMenuProps",
      "DzContextMenuSlots",
      "DzContextMenuTriggerSlots",
      "DzContextMenuContentProps",
      "DzContextMenuContentEmits",
      "DzContextMenuContentSlots",
      "DzContextMenuItemProps",
      "DzContextMenuItemEmits",
      "DzContextMenuItemSlots",
      "DzContextMenuSeparatorSlots",
      "ContextMenuSide",
      "ContextMenuAlign",
      "ContextMenuVariantProps",
      "DzCommandPaletteProps",
      "DzCommandPaletteEmits",
      "DzCommandPaletteSlots",
      "CommandItem",
      "CommandGroup",
      "DzCommandPaletteInputProps",
      "DzCommandPaletteInputSlots",
      "DzCommandPaletteListSlots",
      "DzCommandPaletteItemProps",
      "DzCommandPaletteItemEmits",
      "DzCommandPaletteItemSlots",
      "DzCommandPaletteGroupProps",
      "DzCommandPaletteGroupSlots",
      "DzCommandPaletteEmptySlots",
      "CommandPaletteVariantProps",
      "DzAlertProps",
      "DzAlertEmits",
      "DzAlertSlots",
      "AlertVariantProps",
      "DzBadgeProps",
      "DzBadgeSlots",
      "BadgeVariantProps",
      "DzProgressProps",
      "DzProgressSlots",
      "ProgressTrackVariantProps",
      "ProgressBarVariantProps",
      "DzSpinnerProps",
      "SpinnerVariantProps",
      "DzSkeletonProps",
      "SkeletonVariant",
      "SkeletonVariantProps",
      "DzToastProviderProps",
      "DzToastProviderSlots",
      "DzToastProps",
      "DzToastEmits",
      "DzToastSlots",
      "DzToastViewportProps",
      "DzToastViewportSlots",
      "DzToastContext",
      "ToastItem",
      "ToastVariantProps",
      "DzEmptyProps",
      "DzEmptySlots",
      "EmptyVariantProps",
      "DzResultProps",
      "DzResultSlots",
      "ResultStatus",
      "ResultVariantProps",
      "DzNotificationProps",
      "DzNotificationEmits",
      "DzNotificationSlots",
      "NotificationVariantProps",
      "DzChipProps",
      "DzChipEmits",
      "DzChipSlots",
      "ChipVariantProps",
      "DzTagProps",
      "DzTagEmits",
      "DzTagSlots",
      "TagVariantProps",
      "DzListProps",
      "DzListEmits",
      "DzListSlots",
      "DzListItemProps",
      "DzListItemEmits",
      "DzListItemSlots",
      "DzListContext",
      "ListVariant",
      "ListVariantProps",
      "DzTimelineProps",
      "DzTimelineSlots",
      "DzTimelineItemProps",
      "DzTimelineItemSlots",
      "DzTimelineContext",
      "TimelineVariantProps",
      "DzTableProps",
      "DzTableSlots",
      "DzTableHeaderProps",
      "DzTableHeaderSlots",
      "DzTableBodyProps",
      "DzTableBodySlots",
      "DzTableRowProps",
      "DzTableRowSlots",
      "DzTableCellProps",
      "DzTableCellSlots",
      "DzTableContext",
      "TableDensity",
      "TableVariant",
      "TableVariantProps",
      "DzAccordionSingleProps",
      "DzAccordionMultipleProps",
      "DzAccordionProps",
      "DzAccordionEmits",
      "DzAccordionSlots",
      "DzAccordionItemProps",
      "DzAccordionItemSlots",
      "DzAccordionTriggerProps",
      "DzAccordionTriggerSlots",
      "DzAccordionContentProps",
      "DzAccordionContentSlots",
      "DzAccordionContext",
      "AccordionVariant",
      "AccordionVariantProps",
      "DzDataGridProps",
      "DzDataGridEmits",
      "DzDataGridSlots",
      "DzDataGridHeaderProps",
      "DzDataGridHeaderSlots",
      "DzDataGridBodyProps",
      "DzDataGridBodySlots",
      "DzDataGridRowProps",
      "DzDataGridRowSlots",
      "DzDataGridCellProps",
      "DzDataGridCellSlots",
      "DzDataGridPaginationProps",
      "DzDataGridPaginationEmits",
      "DzDataGridPaginationSlots",
      "DzDataGridContext",
      "ColumnDef",
      "SortModel",
      "SortDirection",
      "PaginationConfig",
      "GridDensity",
      "DataGridVariantProps",
      "DzTreeProps",
      "DzTreeEmits",
      "DzTreeSlots",
      "DzTreeItemProps",
      "DzTreeItemSlots",
      "DzTreeContext",
      "TreeNode",
      "TreeVariantProps",
      "DzIconProps",
      "DzIconSlots",
      "IconSize",
      "DzAvatarProps",
      "DzAvatarEmits",
      "DzAvatarSlots",
      "DzAvatarGroupContext",
      "AvatarShape",
      "AvatarVariantProps",
      "DzAvatarGroupProps",
      "DzAvatarGroupSlots",
      "AvatarGroupVariantProps",
      "AvatarGroupOverflowVariantProps",
      "DzImageProps",
      "DzImageEmits",
      "DzImageSlots",
      "ImageVariantProps",
      "DzCarouselProps",
      "DzCarouselEmits",
      "DzCarouselSlots",
      "DzCarouselSlideProps",
      "DzCarouselSlideSlots",
      "DzCarouselNavProps",
      "DzCarouselNavSlots",
      "DzCarouselDotsProps",
      "DzCarouselDotsSlots",
      "DzCarouselContext",
      "CarouselOrientation",
      "CarouselVariantProps",
      "DzLightboxProps",
      "DzLightboxEmits",
      "DzLightboxSlots",
      "LightboxImage",
      "LightboxVariantProps",
      "DzHeadingProps",
      "DzHeadingSlots",
      "HeadingLevel",
      "HeadingSize",
      "HeadingWeight",
      "HeadingAlign",
      "DzTextProps",
      "DzTextSlots",
      "TextElement",
      "TextSize",
      "TextWeight",
      "TextTone",
      "TextAlign",
      "DzCodeProps",
      "DzCodeSlots",
      "CodeVariant",
      "CodeVariantProps",
      "DzBlockquoteProps",
      "DzBlockquoteSlots",
      "BlockquoteVariantProps",
      "DzCaptionProps",
      "DzCaptionSlots",
      "CaptionTone",
      "CaptionVariantProps",
      "DzFormFieldContext",
      "UseFormFieldOptions",
      "UseDatePickerOptions",
      "UseDatePickerReturn",
      "UseToastReturn",
      "ToastOptions",
      "UseCollapseOptions",
      "UseCollapseReturn",
      "UseDataGridOptions",
      "UseDataGridReturn"
    ]
  }
}
